{
  "roleName": "Azure Edge On-Site Deployment Engineer",
  "type": "BuiltInRole",
  "description": "Grants you access to take actions as an on-site person to assist in the provisioning of an edge device",
  "assignableScopes": [
    "/"
  ],
  "permissions": [
    {
      "actions": [
        "Microsoft.EdgeOrder/bootstrapConfigurations/read",
        "Microsoft.EdgeOrder/bootstrapConfigurations/uploadArtifacts/action"
      ],
      "notActions": [],
      "dataActions": [],
      "notDataActions": []
    }
  ],
  "createdOn": "2024-01-12T11:13:31.4650719Z",
  "updatedOn": "2024-01-12T11:13:31.4650719Z",
  "createdBy": null,
  "updatedBy": null
}
