{
  "roleName": "Elastic SAN Network Admin",
  "type": "BuiltInRole",
  "description": "Allows access to create Private Endpoints on SAN resources, and to read SAN resources",
  "assignableScopes": [
    "/"
  ],
  "permissions": [
    {
      "actions": [
        "Microsoft.ElasticSan/elasticSans/*/read",
        "Microsoft.ElasticSan/elasticSans/PrivateEndpointConnectionsApproval/action",
        "Microsoft.ElasticSan/elasticSans/privateEndpointConnections/write",
        "Microsoft.ElasticSan/elasticSans/privateEndpointConnections/delete",
        "Microsoft.ElasticSan/locations/asyncoperations/read"
      ],
      "notActions": [],
      "dataActions": [],
      "notDataActions": []
    }
  ],
  "createdOn": "2023-07-12T15:16:18.4725463Z",
  "updatedOn": "2023-07-25T15:17:34.8207971Z",
  "createdBy": null,
  "updatedBy": null
}
