{
  "roleName": "Kubernetes Runtime Storage Class Contributor Role",
  "type": "BuiltInRole",
  "description": "Read, write, and delete Kubernetes Runtime storage classes in an Arc connected Kubernetes cluster",
  "assignableScopes": [
    "/"
  ],
  "permissions": [
    {
      "actions": [
        "Microsoft.KubernetesRuntime/storageClasses/read",
        "Microsoft.KubernetesRuntime/storageClasses/write",
        "Microsoft.KubernetesRuntime/storageClasses/delete",
        "Microsoft.Authorization/*/read",
        "Microsoft.Insights/alertRules/*",
        "Microsoft.Resources/deployments/*",
        "Microsoft.Resources/subscriptions/resourceGroups/read"
      ],
      "notActions": [],
      "dataActions": [],
      "notDataActions": []
    }
  ],
  "createdOn": "2023-12-18T16:14:19.6296161Z",
  "updatedOn": "2024-08-20T15:22:00.2579913Z",
  "createdBy": null,
  "updatedBy": null
}
